{
	"section-0_right-to-audit_key1": "தணிக்கை உரிமை",
	"section-0_right-to-audit_key2": "தேர்ந்தெடுக்கப்பட்ட உறுப்பினர்கள் அனைத்து உறுப்பினர்களின் நல்வாழ்வை எளிதாக்குகிறார்கள், எனவே மிகவும் திறமையான தீர்வுகளைக் கண்டறிய அல்லது முரண்பாடுகளை அம்பலப்படுத்த பராமரிக்கப்படும் <b>செயல்முறைகள், கணக்குகள் மற்றும் பதிவுகளை</b> ஆராய உறுப்பினர்களுக்கு அனைத்து உரிமையும் உள்ளது. இந்த நோக்கத்திற்காக உறுப்பினருக்கு சரியான தகவல் கிடைக்க ஏற்பாடு செய்வது சபையின் தனிச்சிறப்பாக இருக்கும். உறுப்பினர் விரும்பினால், அத்தகைய தணிக்கை ஆளுநர் குழுவின் மேற்பார்வையின் கீழ் செய்யப்படலாம்.",
	"section-0_right-to-audit_key3": "கவுன்சில் அதன் முடிவுகளை மின்னணு முறையில் <b>ஆவணப்படுத்த</b> அறிவுறுத்தப்படுகிறது - ஆவணங்கள் மூலமாகவோ அல்லது தகவல்தொடர்பு <span style=\"\">பயன்பாட்டில்</span> உள்ள சேனல்கள் மூலமாகவோ அவை மையத்தின் அனைத்து உறுப்பினர்களுக்கும் மற்றும் கோரிக்கையின் பேரில் மற்றவர்களுக்கும் கிடைக்கும். உறுப்பினர்கள் எதையும் சிறந்த அணுகுமுறையுடன் செய்ய முடியும் என நம்பினால் அல்லது ஏதேனும் தவறான முடிவு எடுக்கப்படுவதாக அவர்கள் நம்பினால் இந்த முடிவுகள் <b>குறித்து கருத்து தெரிவிக்க ஊக்குவிக்கப்படுகிறார்கள்</b> . அவர்கள் தங்கள் &quot;மறுப்பு உரிமை&quot; அல்லது &quot;தணிக்கை செய்யும் உரிமை&quot; ஆகியவற்றைப் பயன்படுத்தி விஷயத்தை அதிகரிக்கலாம்.",
	"section-0_right-to-audit_key4": "அதே நேரத்தில், ஒவ்வொரு மாணவரும் கடைப்பிடிக்க வேண்டிய முக்கியமான கடமைகள் உள்ளன. நவகுருகுலத்தில் உள்ள அனைத்து மாணவர்களின் கடமையாக இருக்க வேண்டும்:",
	"section-0_right-to-audit_key5": "அரசியலமைப்பிற்கு கட்டுப்பட்டு, அரசியலமைப்பால் அமைக்கப்பட்ட அனைத்து செயல்முறைகளையும் விதிகளையும் பின்பற்றவும்",
	"section-0_right-to-audit_key6": "நவகுருகுல் நிலைநிறுத்தப்படும் அனைத்து விழுமியங்களையும் நிலைநிறுத்துதல், அதாவது ஒருவருக்கொருவர் மரியாதை, தவறு நடந்தால் எதிர்த்து நிற்கும் தைரியம், வேலை மற்றும் யோசனைகளில் நேர்மை, வெளிப்படைத்தன்மை மற்றும் வெளிப்படைத்தன்மை, அறியாமையிலிருந்து உண்மைக்கு ஒரு பாதையில் ஒன்றாகச் செல்லுதல்."
}